LICENSE.txt
MANIFEST.in
README
README.md
flask_cdn.py
setup.py
Flask_CDN_Auto.egg-info/PKG-INFO
Flask_CDN_Auto.egg-info/SOURCES.txt
Flask_CDN_Auto.egg-info/dependency_links.txt
Flask_CDN_Auto.egg-info/not-zip-safe
Flask_CDN_Auto.egg-info/requires.txt
Flask_CDN_Auto.egg-info/top_level.txt
tests/__init__.py
tests/test_flask_cdn.py
tests/static/bah.js
tests/static_bp/bah_bp.js